INSTALL.rst
LICENSE
MANIFEST.in
README.rst
VERSION
requirements-dev.txt
requirements.txt
setup.py
src/boilerplate/__init__.py
src/boilerplate/__main__.py
src/boilerplate/__meta__.py
src/boilerplate/commands.py
src/boilerplate/inputs.py
src/boilerplate/__pycache__/__init__.cpython-35.pyc
src/boilerplate/__pycache__/inputs.cpython-35.pyc
src/boilerplate/templates/INSTALL.rst
src/boilerplate/templates/MANIFEST.in
src/boilerplate/templates/README.rst
src/boilerplate/templates/VERSION.txt
src/boilerplate/templates/__main__.py
src/boilerplate/templates/__meta__.py
src/boilerplate/templates/apidoc.rst
src/boilerplate/templates/conf.py
src/boilerplate/templates/gitignore.txt
src/boilerplate/templates/index.rst
src/boilerplate/templates/init.py
src/boilerplate/templates/install.rst
src/boilerplate/templates/license.rst
src/boilerplate/templates/make.bat
src/boilerplate/templates/makefile.txt
src/boilerplate/templates/requirements-dev.txt
src/boilerplate/templates/requirements.txt
src/boilerplate/templates/setup.py
src/boilerplate/templates/test_project.py
src/boilerplate/templates/warning.rst
src/boilerplate/templates/licenses/apache.txt
src/boilerplate/templates/licenses/gpl2.txt
src/boilerplate/templates/licenses/gpl3.txt
src/boilerplate/templates/licenses/lgpl.txt
src/boilerplate/templates/licenses/python.txt
src/boilerplate/test/__init__.py
src/boilerplate/test/test_boilerplate.py
src/pyboilerplate.egg-info/PKG-INFO
src/pyboilerplate.egg-info/SOURCES.txt
src/pyboilerplate.egg-info/dependency_links.txt
src/pyboilerplate.egg-info/entry_points.txt
src/pyboilerplate.egg-info/not-zip-safe
src/pyboilerplate.egg-info/requires.txt
src/pyboilerplate.egg-info/top_level.txt