Metadata-Version: 1.1
Name: pyboilerplate
Version: 0.2.1
Summary: Creates the skeleton of your Python project.
Home-page: https://github.com/fabiommendes/boilerplate
Author: Fábio Macêdo Mendes
Author-email: fabiomacedomendes@gmail.com
License: UNKNOWN
Platform: any
Classifier: Development Status :: 3 - Alpha
Classifier: Intended Audience :: Developers
Classifier: License :: OSI Approved :: GNU General Public License (GPL)
Classifier: Operating System :: POSIX
Classifier: Programming Language :: Python
Classifier: Topic :: Software Development :: Libraries
